LICENSE
README.md
setup.py
src/HACON.egg-info/PKG-INFO
src/HACON.egg-info/SOURCES.txt
src/HACON.egg-info/dependency_links.txt
src/HACON.egg-info/entry_points.txt
src/HACON.egg-info/not-zip-safe
src/HACON.egg-info/requires.txt
src/HACON.egg-info/top_level.txt
src/hacon/__init__.py
src/hacon/hacon.py
src/hacon/wordlists/files-and-dirs.txt
src/hacon/wordlists/subdomains.txt