Metadata-Version: 2.1
Name: HACON
Version: 0.9.1
Summary: Lots of cyber security tool
Home-page: https://github.com/onuratakan/HACON
Author: Onur Atakan ULUSOY
Author-email: atadogan06@gmail.com
License: MIT
Platform: UNKNOWN
Requires-Python: >=3.6
